{
	"name": "em_dept",
	"properties": {
		"linkedServiceName": {
			"referenceName": "AzureBlobStorage1",
			"type": "LinkedServiceReference"
		},
		"annotations": [],
		"type": "DelimitedText",
		"typeProperties": {
			"location": {
				"type": "AzureBlobStorageLocation",
				"fileName": "emp_dept_details.csv",
				"container": "details"
			},
			"columnDelimiter": ",",
			"escapeChar": "\\",
			"firstRowAsHeader": true,
			"quoteChar": "\""
		},
		"schema": [
			{
				"name": "id ",
				"type": "String"
			},
			{
				"name": "name ",
				"type": "String"
			},
			{
				"name": "salary",
				"type": "String"
			},
			{
				"name": "dept_id",
				"type": "String"
			}
		]
	}
}